[
  { "line_id": 9, "station_id": 1 },
  { "line_id": 6, "station_id": 2 },
  { "line_id": 10, "station_id": 3 },
  { "line_id": 2, "station_id": 4 },
  { "line_id": 6, "station_id": 5 },
  { "line_id": 4, "station_id": 6 },
  { "line_id": 11, "station_id": 7 },
  { "line_id": 6, "station_id": 8 },
  { "line_id": 11, "station_id": 9 },
  { "line_id": 2, "station_id": 10 },
  { "line_id": 1, "station_id": 11 },
  { "line_id": 12, "station_id": 12 },
  { "line_id": 8, "station_id": 13 },
  { "line_id": 3, "station_id": 14 },
  { "line_id": 7, "station_id": 4 },
  { "line_id": 4, "station_id": 15 },
  { "line_id": 5, "station_id": 16 },
  { "line_id": 11, "station_id": 17 },
  { "line_id": 12, "station_id": 18 },
  { "line_id": 3, "station_id": 19 },
  { "line_id": 12, "station_id": 20 },
  { "line_id": 3, "station_id": 21 },
  { "line_id": 8, "station_id": 22 },
  { "line_id": 1, "station_id": 23 },
  { "line_id": 9, "station_id": 24 },
  { "line_id": 11, "station_id": 25 },
  { "line_id": 3, "station_id": 26 },
  { "line_id": 2, "station_id": 27 },
  { "line_id": 7, "station_id": 28 },
  { "line_id": 3, "station_id": 29 },
  { "line_id": 6, "station_id": 30 },
  { "line_id": 8, "station_id": 31 },
  { "line_id": 8, "station_id": 32 },
  { "line_id": 3, "station_id": 33 },
  { "line_id": 2, "station_id": 34 },
  { "line_id": 6, "station_id": 35 },
  { "line_id": 11, "station_id": 36 },
  { "line_id": 12, "station_id": 37 },
  { "line_id": 4, "station_id": 38 },
  { "line_id": 11, "station_id": 39 },
  { "line_id": 8, "station_id": 40 },
  { "line_id": 9, "station_id": 41 },
  { "line_id": 3, "station_id": 42 },
  { "line_id": 1, "station_id": 43 },
  { "line_id": 9, "station_id": 34 },
  { "line_id": 8, "station_id": 44 },
  { "line_id": 1, "station_id": 45 },
  { "line_id": 10, "station_id": 46 },
  { "line_id": 11, "station_id": 47 },
  { "line_id": 1, "station_id": 48 },
  { "line_id": 2, "station_id": 49 },
  { "line_id": 3, "station_id": 50 },
  { "line_id": 1, "station_id": 51 },
  { "line_id": 5, "station_id": 52 },
  { "line_id": 9, "station_id": 38 },
  { "line_id": 7, "station_id": 53 },
  { "line_id": 11, "station_id": 54 },
  { "line_id": 11, "station_id": 55 },
  { "line_id": 2, "station_id": 56 },
  { "line_id": 2, "station_id": 57 },
  { "line_id": 9, "station_id": 58 },
  { "line_id": 10, "station_id": 59 },
  { "line_id": 2, "station_id": 60 },
  { "line_id": 2, "station_id": 61 },
  { "line_id": 4, "station_id": 62 },
  { "line_id": 11, "station_id": 63 },
  { "line_id": 1, "station_id": 64 },
  { "line_id": 2, "station_id": 65 },
  { "line_id": 5, "station_id": 66 },
  { "line_id": 6, "station_id": 67 },
  { "line_id": 12, "station_id": 22 },
  { "line_id": 7, "station_id": 68 },
  { "line_id": 12, "station_id": 69 },
  { "line_id": 8, "station_id": 6 },
  { "line_id": 6, "station_id": 30 },
  { "line_id": 7, "station_id": 70 },
  { "line_id": 3, "station_id": 71 },
  { "line_id": 3, "station_id": 72 },
  { "line_id": 4, "station_id": 73 },
  { "line_id": 12, "station_id": 65 },
  { "line_id": 1, "station_id": 3 },
  { "line_id": 9, "station_id": 74 },
  { "line_id": 1, "station_id": 75 },
  { "line_id": 10, "station_id": 76 },
  { "line_id": 5, "station_id": 77 },
  { "line_id": 12, "station_id": 78 },
  { "line_id": 8, "station_id": 34 },
  { "line_id": 4, "station_id": 79 },
  { "line_id": 7, "station_id": 80 },
  { "line_id": 8, "station_id": 81 },
  { "line_id": 11, "station_id": 82 },
  { "line_id": 12, "station_id": 83 },
  { "line_id": 5, "station_id": 84 },
  { "line_id": 12, "station_id": 85 },
  { "line_id": 11, "station_id": 86 },
  { "line_id": 7, "station_id": 87 },
  { "line_id": 12, "station_id": 88 },
  { "line_id": 12, "station_id": 89 },
  { "line_id": 3, "station_id": 90 },
  { "line_id": 2, "station_id": 90 },
  { "line_id": 3, "station_id": 91 },
  { "line_id": 11, "station_id": 92 },
  { "line_id": 11, "station_id": 93 },
  { "line_id": 3, "station_id": 67 },
  { "line_id": 4, "station_id": 94 },
  { "line_id": 7, "station_id": 95 },
  { "line_id": 2, "station_id": 96 },
  { "line_id": 8, "station_id": 97 },
  { "line_id": 2, "station_id": 98 },
  { "line_id": 6, "station_id": 99 },
  { "line_id": 9, "station_id": 3 },
  { "line_id": 4, "station_id": 47 },
  { "line_id": 8, "station_id": 100 },
  { "line_id": 10, "station_id": 101 },
  { "line_id": 8, "station_id": 102 },
  { "line_id": 3, "station_id": 43 },
  { "line_id": 5, "station_id": 103 },
  { "line_id": 10, "station_id": 104 },
  { "line_id": 2, "station_id": 105 },
  { "line_id": 7, "station_id": 106 },
  { "line_id": 12, "station_id": 107 },
  { "line_id": 11, "station_id": 108 },
  { "line_id": 5, "station_id": 109 },
  { "line_id": 8, "station_id": 110 },
  { "line_id": 3, "station_id": 111 },
  { "line_id": 6, "station_id": 112 },
  { "line_id": 6, "station_id": 113 },
  { "line_id": 7, "station_id": 114 },
  { "line_id": 8, "station_id": 108 },
  { "line_id": 7, "station_id": 115 },
  { "line_id": 12, "station_id": 115 },
  { "line_id": 5, "station_id": 116 },
  { "line_id": 6, "station_id": 70 },
  { "line_id": 5, "station_id": 39 },
  { "line_id": 12, "station_id": 117 },
  { "line_id": 2, "station_id": 102 },
  { "line_id": 8, "station_id": 118 },
  { "line_id": 9, "station_id": 119 },
  { "line_id": 1, "station_id": 120 },
  { "line_id": 8, "station_id": 121 },
  { "line_id": 8, "station_id": 122 },
  { "line_id": 10, "station_id": 123 },
  { "line_id": 12, "station_id": 124 },
  { "line_id": 1, "station_id": 114 },
  { "line_id": 2, "station_id": 125 },
  { "line_id": 11, "station_id": 126 },
  { "line_id": 3, "station_id": 127 },
  { "line_id": 1, "station_id": 128 },
  { "line_id": 2, "station_id": 129 },
  { "line_id": 3, "station_id": 130 },
  { "line_id": 6, "station_id": 131 },
  { "line_id": 12, "station_id": 132 },
  { "line_id": 1, "station_id": 133 },
  { "line_id": 2, "station_id": 134 },
  { "line_id": 5, "station_id": 135 },
  { "line_id": 1, "station_id": 79 },
  { "line_id": 7, "station_id": 136 },
  { "line_id": 3, "station_id": 137 },
  { "line_id": 11, "station_id": 138 },
  { "line_id": 12, "station_id": 139 },
  { "line_id": 1, "station_id": 86 },
  { "line_id": 10, "station_id": 140 },
  { "line_id": 2, "station_id": 141 },
  { "line_id": 1, "station_id": 142 },
  { "line_id": 9, "station_id": 42 },
  { "line_id": 5, "station_id": 94 },
  { "line_id": 1, "station_id": 125 },
  { "line_id": 1, "station_id": 44 },
  { "line_id": 7, "station_id": 143 },
  { "line_id": 7, "station_id": 144 },
  { "line_id": 2, "station_id": 145 },
  { "line_id": 11, "station_id": 146 },
  { "line_id": 11, "station_id": 71 },
  { "line_id": 12, "station_id": 147 },
  { "line_id": 12, "station_id": 50 },
  { "line_id": 3, "station_id": 148 },
  { "line_id": 8, "station_id": 149 },
  { "line_id": 4, "station_id": 150 },
  { "line_id": 10, "station_id": 151 },
  { "line_id": 5, "station_id": 3 },
  { "line_id": 2, "station_id": 152 },
  { "line_id": 8, "station_id": 153 },
  { "line_id": 11, "station_id": 154 },
  { "line_id": 2, "station_id": 155 },
  { "line_id": 10, "station_id": 156 },
  { "line_id": 3, "station_id": 157 },
  { "line_id": 2, "station_id": 158 },
  { "line_id": 9, "station_id": 159 },
  { "line_id": 2, "station_id": 160 },
  { "line_id": 4, "station_id": 5 },
  { "line_id": 3, "station_id": 52 },
  { "line_id": 1, "station_id": 161 },
  { "line_id": 11, "station_id": 162 },
  { "line_id": 1, "station_id": 163 },
  { "line_id": 9, "station_id": 114 }
]